README.md
setup.cfg
setup.py
quotient_security_check.egg-info/PKG-INFO
quotient_security_check.egg-info/SOURCES.txt
quotient_security_check.egg-info/dependency_links.txt
quotient_security_check.egg-info/requires.txt
quotient_security_check.egg-info/top_level.txt
security/__init__.py
security/check_ip.py
security/okta_token_check.py